<?xml version="1.0" encoding="utf-8" ?>
<dwsync>
<file name="SpryMenuBar.js" server="suwebmaster.net//_sites/centroeuropeodeldolordeespalda/bo/" local="128694437720000000" remote="129212221800000000" />
<file name="SpryMenuBarDown.gif" server="suwebmaster.net//_sites/centroeuropeodeldolordeespalda/bo/" local="128694437720000000" remote="129212221800000000" />
<file name="SpryMenuBarDownHover.gif" server="suwebmaster.net//_sites/centroeuropeodeldolordeespalda/bo/" local="129052336540000000" remote="129212221800000000" />
<file name="SpryMenuBarHorizontal.css" server="suwebmaster.net//_sites/centroeuropeodeldolordeespalda/bo/" local="129052340680000000" remote="129212221800000000" />
<file name="SpryMenuBarRight.gif" server="suwebmaster.net//_sites/centroeuropeodeldolordeespalda/bo/" local="128694437720000000" remote="129212221800000000" />
<file name="SpryMenuBarRightHover.gif" server="suwebmaster.net//_sites/centroeuropeodeldolordeespalda/bo/" local="128694437720000000" remote="129212221800000000" />
<file name="SpryMenuBarDown.gif" server="suwebmaster.net//_sites/buskateka/" local="128694437720000000" remote="129267966600000000" />
<file name="SpryMenuBarRight.gif" server="suwebmaster.net//_sites/buskateka/" local="128694437720000000" remote="129267966600000000" />
<file name="SpryMenuBarDownHover.gif" server="suwebmaster.net//_sites/buskateka/" local="129052336540000000" remote="129267966600000000" />
<file name="SpryMenuBarRightHover.gif" server="suwebmaster.net//_sites/buskateka/" local="128694437720000000" remote="129267966600000000" />
<file name="SpryMenuBarHorizontal.css" server="suwebmaster.net//_sites/buskateka/" local="129267998313378544" remote="129267966600000000" />
</dwsync>